gast/__init__.py
gast/ast2.py
gast/ast3.py
gast/astn.py
gast/gast.py
gast/unparser.py
gast/version.py
gast-0.5.3.dist-info/LICENSE
gast-0.5.3.dist-info/METADATA
gast-0.5.3.dist-info/WHEEL
gast-0.5.3.dist-info/top_level.txt
gast-0.5.3.dist-info/RECORD
